SupervisedGRN/__init__.py
SupervisedGRN/ann.py
SupervisedGRN/cnn.py
SupervisedGRN/data.py
SupervisedGRN/hybrid.py
SupervisedGRN/ml.py
SupervisedGRN-0.0.1.dist-info/LICENSE
SupervisedGRN-0.0.1.dist-info/METADATA
SupervisedGRN-0.0.1.dist-info/WHEEL
SupervisedGRN-0.0.1.dist-info/top_level.txt
SupervisedGRN-0.0.1.dist-info/RECORD
