Metadata-Version: 2.1
Name: SupervisedGRN
Version: 0.0.1
Summary: This package leverages both supervised machine learning and deep learning techniques to construct robust predictive models from transcriptomic data. It is designed to train on this high-dimensional data, extract key features, and make accurate predictions. The models generated can be used to uncover complex biological relationships and predict outcomes such as gene regulatory network behaviors, offering valuable insights for genomics and bioinformatics research.
Author-email: Sai Teja Mummadi <mummadi@edu.com>
Project-URL: Homepage, https://github.com/SaiTejaMummadi/SupervisedGRN
Project-URL: Bug Tracker, https://github.com/SaiTejaMummadi/SupervisedGRN/issues
Classifier: Programming Language :: Python :: 3
Classifier: License :: OSI Approved :: MIT License
Classifier: Operating System :: OS Independent
Requires-Python: >=3.7
License-File: LICENSE
Requires-Dist: pandas
Requires-Dist: numpy
Requires-Dist: keras
Requires-Dist: seaborn
Requires-Dist: matplotlib
Requires-Dist: tensorflow
Requires-Dist: scikit-learn
